dracklib/__init__.py
dracklib/eventlog.py
dracklib/rc.py
dracklib/utils.py
dracklib-0.0.1.dist-info/METADATA
dracklib-0.0.1.dist-info/WHEEL
dracklib-0.0.1.dist-info/entry_points.txt
dracklib-0.0.1.dist-info/licenses/LICENSE
dracklib-0.0.1.dist-info/RECORD
