Metadata-Version: 2.4
Name: dracklib
Version: 0.0.1
Summary: My collection of useful Python stuff.
Project-URL: Repository, https://github.com/DrackThor/dracklib
Author-email: Daniel Drack <daniel@drackthor.me>
License-Expression: MIT
License-File: LICENSE
Classifier: Development Status :: 4 - Beta
Classifier: Intended Audience :: Developers
Classifier: Operating System :: OS Independent
Classifier: Programming Language :: Python
Classifier: Programming Language :: Python :: 3
Classifier: Programming Language :: Python :: 3.11
Classifier: Programming Language :: Python :: 3.12
Classifier: Programming Language :: Python :: 3.13
Classifier: Typing :: Typed
Requires-Python: <4.0,>=3.11
